kicad_symbol_tool/__init__.py
kicad_symbol_tool/cli.py
kicad_symbol_tool/derived_parts_from_spreadsheet.py
kicad_symbol_tool-1.0.1.dist-info/licenses/LICENSE
kicad_symbol_tool-1.0.1.dist-info/METADATA
kicad_symbol_tool-1.0.1.dist-info/WHEEL
kicad_symbol_tool-1.0.1.dist-info/entry_points.txt
kicad_symbol_tool-1.0.1.dist-info/top_level.txt
kicad_symbol_tool-1.0.1.dist-info/RECORD
