Metadata-Version: 2.4
Name: kicad-symbol-tool
Version: 1.0.1
Summary: A command-line tool that assists with managing KiCad part libraries
Requires-Python: >=3.12
License-File: LICENSE
Requires-Dist: kicad-symlib-utility>=1.0.0
Requires-Dist: openpyxl>=3.1.5
Requires-Dist: pandas>=2.3.2
Requires-Dist: pandas-stubs>=2.3.2.250827
Requires-Dist: sexpdata>=1.0.2
Requires-Dist: typer>=0.17.4
Dynamic: license-file
